mydummylib/package1/main.cp38-win_amd64.pyd
mydummylib/package2/main.cp38-win_amd64.pyd
my_personal_dummy_lib-0.0.16.dist-info/METADATA
my_personal_dummy_lib-0.0.16.dist-info/WHEEL
my_personal_dummy_lib-0.0.16.dist-info/top_level.txt
my_personal_dummy_lib-0.0.16.dist-info/RECORD
